HISTORY.rst
LICENSE.txt
MANIFEST.in
README.rst
setup.py
test_schedule.py
cronlikescheduler.egg-info/PKG-INFO
cronlikescheduler.egg-info/SOURCES.txt
cronlikescheduler.egg-info/dependency_links.txt
cronlikescheduler.egg-info/top_level.txt
schedule/__init__.py