Metadata-Version: 1.1
Name: cronlikescheduler
Version: 0.5.2
Summary: Job scheduling for humans.
Home-page: https://github.com/lordoftheflies/cronlikescheduler
Author: Daniel Bader
Author-email: mail@dbader.org
License: MIT
Download-URL: https://github.com/lordoftheflies/cronlikescheduler/tarball/0.5.2
Keywords: schedule,periodic,jobs,scheduling,clockwork,cron
Platform: UNKNOWN
Classifier: Intended Audience :: Developers
Classifier: License :: OSI Approved :: MIT License
Classifier: Programming Language :: Python :: 2.7
Classifier: Programming Language :: Python :: 3.5
Classifier: Natural Language :: English
